{
  "type": "goety:ritual",
  "ritual_type": "goety:craft",
  "activation_item": {
    "item": "goety:darkrobe"
  },
  "craftType": "necroturgy",
  "soulCost": 1,
  "duration": 10,
  "ingredients": [
    {
      "item": "minecraft:skeleton_skull"
    },
    {
      "item": "minecraft:skeleton_skull"
    },
    {
      "item": "minecraft:lapis_lazuli"
    },
    {
      "item": "minecraft:lapis_lazuli"
    },
    {
      "item": "minecraft:bone"
    }
  ],
  "result": {
    "item": "goety:necrorobe"
  }
}
